falcon_mcp_server/__about__.py
falcon_mcp_server/__init__.py
falcon_mcp_server/constants.py
falcon_mcp_server/errors.py
falcon_mcp_server/logger.py
falcon_mcp_server/mcp.py
falcon_mcp_server/serve.py
falcon_mcp_server/server/__init__.py
falcon_mcp_server/server/resources.py
falcon_mcp_server/server/server.py
falcon_mcp_server/server/tools.py
falcon_mcp_server/session/__init__.py
falcon_mcp_server/session/session.py
falcon_mcp_server/session/storage.py
falcon_mcp_server/transport/__init__.py
falcon_mcp_server/transport/streamablehttp.py
falcon_mcp_server/transport/toon.py
falcon_mcp_server-0.1.0.dist-info/METADATA
falcon_mcp_server-0.1.0.dist-info/WHEEL
falcon_mcp_server-0.1.0.dist-info/entry_points.txt
falcon_mcp_server-0.1.0.dist-info/licenses/LICENSE
falcon_mcp_server-0.1.0.dist-info/RECORD
