Metadata-Version: 2.4
Name: falcon-mcp-server
Version: 0.1.0
Summary: MCP server component for Falcon apps.
Project-URL: Issues, https://github.com/falconry/falcon-mcp-server/issues
Project-URL: Source, https://github.com/falconry/falcon-mcp-server
Author-email: Vytautas Liuolia <vytautas.liuolia@gmail.com>
License-Expression: Apache-2.0
License-File: LICENSE
Classifier: Development Status :: 2 - Pre-Alpha
Classifier: Programming Language :: Python
Classifier: Programming Language :: Python :: 3.10
Classifier: Programming Language :: Python :: 3.11
Classifier: Programming Language :: Python :: 3.12
Classifier: Programming Language :: Python :: 3.13
Classifier: Programming Language :: Python :: 3.14
Classifier: Programming Language :: Python :: Implementation :: CPython
Classifier: Programming Language :: Python :: Implementation :: PyPy
Requires-Python: >=3.10
Requires-Dist: falcon>=4.2
Provides-Extra: serve
Requires-Dist: pyyaml; extra == 'serve'
Requires-Dist: uvicorn; extra == 'serve'
